eegAudioAnotator/__init__.py
eegAudioAnotator/config.py
eegAudioAnotator/main.py
eegAudioAnotator/classes/__init__.py
eegAudioAnotator/classes/audio.py
eegAudioAnotator/classes/eeg.py
eegAudioAnotator/classes/eeg_audio.py
eegAudioAnotator/classes/utils.py
eegAudioAnotator/gui/__init__.py
eegAudioAnotator/gui/main_display.py
eegAudioAnotator/gui/mapping_display.py
eegAudioAnotator/gui/mapping_display1.py
eegAudioAnotator/gui/utils.py
eegAudioAnotator/gui/Images/__init__.py
eegAudioAnotator-1.0.0.dist-info/LICENSE.lic
eegAudioAnotator-1.0.0.dist-info/METADATA
eegAudioAnotator-1.0.0.dist-info/WHEEL
eegAudioAnotator-1.0.0.dist-info/entry_points.txt
eegAudioAnotator-1.0.0.dist-info/top_level.txt
eegAudioAnotator-1.0.0.dist-info/RECORD
